pylint_docstring_checker/__init__.py
pylint_docstring_checker/class_docstring_checker.py
pylint_docstring_checker/docstring_checker_base.py
pylint_docstring_checker/function_docstring_checker.py
pylint_docstring_checker-1.0.6.dist-info/licenses/LICENSE
pylint_docstring_checker-1.0.6.dist-info/METADATA
pylint_docstring_checker-1.0.6.dist-info/WHEEL
pylint_docstring_checker-1.0.6.dist-info/entry_points.txt
pylint_docstring_checker-1.0.6.dist-info/top_level.txt
pylint_docstring_checker-1.0.6.dist-info/RECORD
