Metadata-Version: 2.4
Name: pylint-docstring-checker
Version: 1.0.6
Summary: A Pylint plugin to check Google-style docstrings and language detection.
Author-email: AI&T <contact@ai-t.vn>
License: MIT
Keywords: pylint,docstring,google style,linter
Classifier: Programming Language :: Python :: 3
Classifier: License :: OSI Approved :: MIT License
Classifier: Operating System :: OS Independent
Requires-Python: >=3.9
License-File: LICENSE
Dynamic: license-file
